layouttree/__init__.py
layouttree/dtree.py
layouttree-0.1.7.dist-info/METADATA
layouttree-0.1.7.dist-info/WHEEL
layouttree-0.1.7.dist-info/top_level.txt
layouttree-0.1.7.dist-info/RECORD
