Metadata-Version: 2.1
Name: layouttree
Version: 0.1.7
Summary: Build layout using tree
Home-page: https://github.com/pbcquoc/layouttree
Author: pbcquoc
Author-email: pbcquoc@gmail.com
License: UNKNOWN
Platform: UNKNOWN
Classifier: Programming Language :: Python :: 3
Classifier: License :: OSI Approved :: MIT License
Classifier: Operating System :: OS Independent
Requires-Python: >=3.6
Requires-Dist: anytree (==2.8.0)
Requires-Dist: apted (==1.0.3)
